{"entities":{"2f316c26-2da8-4bd5-8ab8-91e2e0b137a0":{"name":"9","tags":["player"],"enabled":true,"resource_id":"2f316c26-2da8-4bd5-8ab8-91e2e0b137a0","parent":null,"children":["29d23efa-e972-4d92-95c0-34413858a1fa","5e77df4f-4d09-45df-a9a6-35f13e6f4e28"],"position":[-366.1314392089844,75.03130340576172,-103.28785705566406],"rotation":[180,-17.499999802305275,180],"scale":[1,1,1],"components":{"script":{"enabled":true,"order":["coPlayer"],"scripts":{"coPlayer":{"enabled":true,"attributes":{"physicsEntity":"29d23efa-e972-4d92-95c0-34413858a1fa","graphicsEntity":"5e77df4f-4d09-45df-a9a6-35f13e6f4e28","camera":"0ed6bf28-541e-4c76-8b4e-29da98e65bf5","playerText":"fb906e15-4913-455c-8151-5a75daa0acc5","totemSphereEntity":"ac1d96f3-f453-4361-b30f-bb28e21e4755"}}}}}},"29d23efa-e972-4d92-95c0-34413858a1fa":{"name":"Car Physics","tags":["player"],"enabled":true,"resource_id":"29d23efa-e972-4d92-95c0-34413858a1fa","parent":"2f316c26-2da8-4bd5-8ab8-91e2e0b137a0","children":["1284d79e-6c01-47da-b13e-1cdd01b45322","760f19ce-1a41-487f-ba1d-6ae267d57620","0abb5ca2-a9ac-441d-b262-cc9ecc2f119a","2060d006-bdb6-4d9c-8055-e1554c144a3f","087dfb00-791d-421f-bfc4-367c83a3d219","d508add7-e698-4075-ab0a-b78be994052f","d331554b-46cf-4034-870d-7746b93cad83","694b709a-621d-4eaa-bb4b-e2ead2053ab0","227e721d-750d-4910-ae0a-1c4eb7af8e02","d2097f95-5fbc-4d03-8949-1c5e7f52dfc6","abb38206-7ce9-4d09-ba50-7da3e117700a","63b1d88f-d05b-4f0e-a815-0052bc1edf2b","f94b5413-01a6-4946-9e62-ae80f911e488","93abe788-8004-4b59-b6f6-d6cf8719b94e"],"position":[0,0,0],"rotation":[0,73.12,0],"scale":[1,1,1],"components":{"script":{"enabled":true,"order":["vehicle","vehicleControls","coPlayerFlagFounder","coSoundController"],"scripts":{"vehicle":{"enabled":true,"attributes":{"wheels":["d508add7-e698-4075-ab0a-b78be994052f","d331554b-46cf-4034-870d-7746b93cad83","694b709a-621d-4eaa-bb4b-e2ead2053ab0","227e721d-750d-4910-ae0a-1c4eb7af8e02"],"maxEngineForce":3750,"maxBrakingForce":300,"maxSteering":0.45,"minSteering":0.1,"maxCarSpeed":100,"maxCarBackSpeed":25}},"vehicleControls":{"enabled":true,"attributes":{"targetVehicle":"29d23efa-e972-4d92-95c0-34413858a1fa","leftButton":null,"rightButton":null,"forwardButton":null,"reverseButton":null}},"coPlayerFlagFounder":{"enabled":true,"attributes":{}},"coSoundController":{"enabled":true,"attributes":{}}}},"rigidbody":{"enabled":true,"type":"dynamic","mass":800,"linearDamping":0,"angularDamping":0,"linearFactor":[1,1,1],"angularFactor":[1,1,1],"friction":1,"restitution":0.5},"collision":{"enabled":true,"type":"compound","halfExtents":[1,0.5,2],"radius":0.5,"axis":1,"height":2,"asset":null,"renderAsset":null,"linearOffset":[0,0,0],"angularOffset":[0,0,0]},"sound":{"enabled":true,"volume":1,"pitch":1,"positional":false,"refDistance":1,"maxDistance":10000,"rollOffFactor":1,"distanceModel":"linear","slots":{"1":{"name":"carDrive","loop":true,"autoPlay":false,"overlap":false,"asset":152048971,"startTime":0,"duration":null,"volume":0.67,"pitch":1}}}}},"760f19ce-1a41-487f-ba1d-6ae267d57620":{"name":"Chassis","tags":[],"enabled":true,"resource_id":"760f19ce-1a41-487f-ba1d-6ae267d57620","parent":"29d23efa-e972-4d92-95c0-34413858a1fa","children":[],"position":[-0.45932009144702324,0.96563720703125,-0.2890115239263764],"rotation":[0,0,0],"scale":[1,1,1],"components":{"collision":{"enabled":true,"type":"capsule","halfExtents":[0.6,0.35,1.65],"radius":0.58,"axis":2,"height":4.43,"asset":null,"renderAsset":null,"linearOffset":[0,0,0],"angularOffset":[0,0,0]}}},"0abb5ca2-a9ac-441d-b262-cc9ecc2f119a":{"name":"Chassis","tags":["player"],"enabled":true,"resource_id":"0abb5ca2-a9ac-441d-b262-cc9ecc2f119a","parent":"29d23efa-e972-4d92-95c0-34413858a1fa","children":[],"position":[0.49147549559682346,0.96563720703125,-0.2770628561426065],"rotation":[0,0,0],"scale":[1,1,1],"components":{"collision":{"enabled":true,"type":"capsule","halfExtents":[0.6,0.35,1.65],"radius":0.58,"axis":2,"height":4.43,"asset":null,"renderAsset":null,"linearOffset":[0,0,0],"angularOffset":[0,0,0]}}},"2060d006-bdb6-4d9c-8055-e1554c144a3f":{"name":"Cab","tags":[],"enabled":true,"resource_id":"2060d006-bdb6-4d9c-8055-e1554c144a3f","parent":"29d23efa-e972-4d92-95c0-34413858a1fa","children":[],"position":[0,1.245,-0.14],"rotation":[0,0,0],"scale":[1,1,1],"components":{"collision":{"enabled":true,"type":"box","halfExtents":[0.5,0.25,0.4],"radius":0.5,"axis":1,"height":2,"asset":null,"renderAsset":null,"linearOffset":[0,0,0],"angularOffset":[0,0,0]}}},"087dfb00-791d-421f-bfc4-367c83a3d219":{"name":"Lights","tags":[],"enabled":false,"resource_id":"087dfb00-791d-421f-bfc4-367c83a3d219","parent":"29d23efa-e972-4d92-95c0-34413858a1fa","children":[],"position":[0,1.573752492780053,-0.0605667307972908],"rotation":[0,0,0],"scale":[1,1,1],"components":{"collision":{"enabled":true,"type":"box","halfExtents":[0.35,0.08,0.05],"radius":0.5,"axis":1,"height":2,"asset":null,"renderAsset":null,"linearOffset":[0,0,0],"angularOffset":[0,0,0]}}},"d508add7-e698-4075-ab0a-b78be994052f":{"name":"Front Left Wheel","tags":[],"enabled":true,"resource_id":"d508add7-e698-4075-ab0a-b78be994052f","parent":"29d23efa-e972-4d92-95c0-34413858a1fa","children":[],"position":[0.89561362955628,0.608001708984304,1.532557856358153],"rotation":[0,0,0],"scale":[1,1,1],"components":{"script":{"enabled":true,"order":["vehicleWheel"],"scripts":{"vehicleWheel":{"enabled":true,"attributes":{"isFront":true,"radius":0.4,"width":0.4,"suspensionStiffness":40,"suspensionDamping":2.3,"suspensionCompression":4.4,"suspensionRestLength":0.2,"rollInfluence":0.2,"frictionSlip":1000,"debugRender":false}}}}}},"d331554b-46cf-4034-870d-7746b93cad83":{"name":"Front Right Wheel","tags":[],"enabled":true,"resource_id":"d331554b-46cf-4034-870d-7746b93cad83","parent":"29d23efa-e972-4d92-95c0-34413858a1fa","children":[],"position":[-0.8611510936625564,0.608001708984304,1.523529434063505],"rotation":[0,0,0],"scale":[1,1,1],"components":{"script":{"enabled":true,"order":["vehicleWheel"],"scripts":{"vehicleWheel":{"enabled":true,"attributes":{"isFront":true,"radius":0.4,"width":0.4,"suspensionStiffness":40,"suspensionDamping":2.3,"suspensionCompression":4.4,"suspensionRestLength":0.2,"rollInfluence":0.2,"frictionSlip":1000,"debugRender":false}}}}}},"694b709a-621d-4eaa-bb4b-e2ead2053ab0":{"name":"Back Left Wheel","tags":[],"enabled":true,"resource_id":"694b709a-621d-4eaa-bb4b-e2ead2053ab0","parent":"29d23efa-e972-4d92-95c0-34413858a1fa","children":[],"position":[0.9526360493101151,0.608,-1.598104360408911],"rotation":[0,0,0],"scale":[1,1,1],"components":{"script":{"enabled":true,"order":["vehicleWheel"],"scripts":{"vehicleWheel":{"enabled":true,"attributes":{"isFront":true,"radius":0.4,"width":0.4,"suspensionStiffness":40,"suspensionDamping":2.3,"suspensionCompression":4.4,"suspensionRestLength":0.2,"rollInfluence":0.2,"frictionSlip":1000,"debugRender":false}}}}}},"227e721d-750d-4910-ae0a-1c4eb7af8e02":{"name":"Back Right Wheel","tags":[],"enabled":true,"resource_id":"227e721d-750d-4910-ae0a-1c4eb7af8e02","parent":"29d23efa-e972-4d92-95c0-34413858a1fa","children":[],"position":[-0.9155826754600866,0.608,-1.5864901707268473],"rotation":[0,0,0],"scale":[1,1,1],"components":{"script":{"enabled":true,"order":["vehicleWheel"],"scripts":{"vehicleWheel":{"enabled":true,"attributes":{"isFront":true,"radius":0.4,"width":0.4,"suspensionStiffness":40,"suspensionDamping":2.3,"suspensionCompression":4.4,"suspensionRestLength":0.2,"rollInfluence":0.2,"frictionSlip":1000,"debugRender":false}}}}}},"d2097f95-5fbc-4d03-8949-1c5e7f52dfc6":{"name":"Camera Axis","tags":[],"enabled":true,"resource_id":"d2097f95-5fbc-4d03-8949-1c5e7f52dfc6","parent":"29d23efa-e972-4d92-95c0-34413858a1fa","children":["0ed6bf28-541e-4c76-8b4e-29da98e65bf5","73bf7be0-3e45-4a97-9e4f-26d6108886f4"],"position":[0,1,0],"rotation":[0,0,0],"scale":[1,1,1],"components":{}},"0ed6bf28-541e-4c76-8b4e-29da98e65bf5":{"name":"Camera","tags":[],"enabled":true,"resource_id":"0ed6bf28-541e-4c76-8b4e-29da98e65bf5","parent":"d2097f95-5fbc-4d03-8949-1c5e7f52dfc6","children":[],"position":[0,0,25],"rotation":[0,0,-2.670532062154507e-8],"scale":[1,1,1],"components":{"camera":{"enabled":true,"clearColorBuffer":true,"clearColor":[0.20784313725490197,0.20784313725490197,0.20784313725490197,1],"clearDepthBuffer":true,"renderSceneDepthMap":false,"renderSceneColorMap":false,"projection":0,"fov":45,"frustumCulling":true,"orthoHeight":100,"nearClip":0.3,"farClip":1000,"priority":0,"rect":[0,0,1,1],"layers":[0,1,2,3,4]},"script":{"enabled":true,"order":["coCameraController","coMobileCameraController"],"scripts":{"coCameraController":{"enabled":false,"attributes":{"mouseSpeed":5,"raycastEndPoint":"73bf7be0-3e45-4a97-9e4f-26d6108886f4","vehicleParentEntity":"2f316c26-2da8-4bd5-8ab8-91e2e0b137a0"}},"coMobileCameraController":{"enabled":false,"attributes":{"touchLookSensitivity":5,"raycastEndPoint":"73bf7be0-3e45-4a97-9e4f-26d6108886f4","snappinessFactor":0.1}}}}}},"73bf7be0-3e45-4a97-9e4f-26d6108886f4":{"name":"RaycastEndPoint","tags":[],"enabled":true,"resource_id":"73bf7be0-3e45-4a97-9e4f-26d6108886f4","parent":"d2097f95-5fbc-4d03-8949-1c5e7f52dfc6","children":[],"position":[0,0,25],"rotation":[0,0,0],"scale":[1,1,1],"components":{}},"abb38206-7ce9-4d09-ba50-7da3e117700a":{"name":"Grid Screen","tags":[],"enabled":true,"resource_id":"abb38206-7ce9-4d09-ba50-7da3e117700a","parent":"29d23efa-e972-4d92-95c0-34413858a1fa","children":["fb906e15-4913-455c-8151-5a75daa0acc5"],"position":[1.4901161193847656e-8,2.5,0],"rotation":[-89.99999999168251,0,0],"scale":[0.01,0.01,0.01],"components":{"screen":{"enabled":true,"screenSpace":false,"scaleMode":"blend","scaleBlend":0.5,"resolution":[1920,1080],"referenceResolution":[1920,1080],"priority":1},"script":{"enabled":true,"order":[],"scripts":{}}}},"fb906e15-4913-455c-8151-5a75daa0acc5":{"name":"Username","tags":[],"enabled":true,"resource_id":"fb906e15-4913-455c-8151-5a75daa0acc5","parent":"abb38206-7ce9-4d09-ba50-7da3e117700a","children":[],"position":[0,0.0003878467523463769,0],"rotation":[89.99999999168251,-1.684455038776394e-15,3.386694602270383e-8],"scale":[1,1,1],"components":{"element":{"enabled":true,"type":"text","anchor":[0.5,0.5,0.5,0.5],"pivot":[0.5,0.5],"text":"","key":null,"fontAsset":152048468,"fontSize":50,"minFontSize":0,"maxFontSize":12,"autoFitWidth":false,"autoFitHeight":false,"maxLines":null,"lineHeight":32,"wrapLines":false,"spacing":1,"color":[1,1,1],"opacity":1,"textureAsset":null,"spriteAsset":null,"spriteFrame":0,"pixelsPerUnit":null,"width":2.103,"height":12,"margin":[-78.862,-6,-78.862,-6],"alignment":[0,0.5],"outlineColor":[0,0,0,1],"outlineThickness":1,"shadowColor":[0,0,0,1],"shadowOffset":[0.25,-0.25],"rect":[0,0,1,1],"materialAsset":null,"autoWidth":true,"autoHeight":false,"fitMode":"stretch","useInput":false,"batchGroupId":null,"mask":false,"layers":[0],"enableMarkup":false},"script":{"enabled":true,"order":["coLookAtCamera"],"scripts":{"coLookAtCamera":{"enabled":true,"attributes":{"angle":[180,0,180],"client":false}}}}}},"5e77df4f-4d09-45df-a9a6-35f13e6f4e28":{"name":"Car Graphics","tags":[],"enabled":true,"resource_id":"5e77df4f-4d09-45df-a9a6-35f13e6f4e28","parent":"2f316c26-2da8-4bd5-8ab8-91e2e0b137a0","children":["d8e840fd-ff2d-4e15-9fd9-05e4d2a1b643","84640bf0-2a33-46a4-9c62-202ca32c5c48","ef98a74e-f2b9-43c3-926a-c1d3ff38adc2","89d758a7-5c33-498b-8b96-e9a729d7f80d","1b5a3b78-f2c5-4a75-8839-a0a94411e2de","ac1d96f3-f453-4361-b30f-bb28e21e4755"],"position":[0,0,0],"rotation":[0,73.12,0],"scale":[0.01,0.01,0.01],"components":{"script":{"enabled":true,"order":["vehicleGraphics"],"scripts":{"vehicleGraphics":{"enabled":true,"attributes":{"physicsVehicle":"29d23efa-e972-4d92-95c0-34413858a1fa","wheelNames":["FL_Wheel","FR_Wheel","BL_Wheel","BR_Wheel"],"wheelOffsets":[[-0.1,0,0],[0.1,0,0],[-0.1,0,0],[0.1,0,0]]}}}}}},"d8e840fd-ff2d-4e15-9fd9-05e4d2a1b643":{"name":"Body","tags":[],"enabled":true,"resource_id":"d8e840fd-ff2d-4e15-9fd9-05e4d2a1b643","parent":"5e77df4f-4d09-45df-a9a6-35f13e6f4e28","children":[],"position":[0,29.7,0],"rotation":[0,0,0],"scale":[1,1,1],"components":{"render":{"enabled":true,"type":"asset","asset":152048792,"materialAssets":[152048803,152048467,152048467],"layers":[0],"batchGroupId":null,"castShadows":false,"castShadowsLightmap":false,"receiveShadows":false,"lightmapped":false,"lightmapSizeMultiplier":1,"castShadowsLightMap":true,"lightMapped":false,"lightMapSizeMultiplier":1,"isStatic":false,"rootBone":null}}},"84640bf0-2a33-46a4-9c62-202ca32c5c48":{"name":"FR_Wheel","tags":[],"enabled":true,"resource_id":"84640bf0-2a33-46a4-9c62-202ca32c5c48","parent":"5e77df4f-4d09-45df-a9a6-35f13e6f4e28","children":[],"position":[-85.21657265413887,57.48974609374363,152.55744041645812],"rotation":[0,0,0],"scale":[1,1,1],"components":{"render":{"enabled":true,"type":"asset","asset":152048761,"materialAssets":[152048467],"layers":[0],"batchGroupId":null,"castShadows":true,"castShadowsLightmap":true,"receiveShadows":true,"lightmapped":false,"lightmapSizeMultiplier":1,"castShadowsLightMap":true,"lightMapped":false,"lightMapSizeMultiplier":1,"isStatic":false,"rootBone":null}}},"ef98a74e-f2b9-43c3-926a-c1d3ff38adc2":{"name":"BR_Wheel","tags":[],"enabled":true,"resource_id":"ef98a74e-f2b9-43c3-926a-c1d3ff38adc2","parent":"5e77df4f-4d09-45df-a9a6-35f13e6f4e28","children":[],"position":[-88.51219936108646,55.888959587961835,-158.84244722309086],"rotation":[0,0,0],"scale":[1,1,1],"components":{"render":{"enabled":true,"type":"asset","asset":152048761,"materialAssets":[152048467],"layers":[0],"batchGroupId":null,"castShadows":true,"castShadowsLightmap":true,"receiveShadows":true,"lightmapped":false,"lightmapSizeMultiplier":1,"castShadowsLightMap":true,"lightMapped":false,"lightMapSizeMultiplier":1,"isStatic":false,"rootBone":null}}},"89d758a7-5c33-498b-8b96-e9a729d7f80d":{"name":"FL_Wheel","tags":[],"enabled":true,"resource_id":"89d758a7-5c33-498b-8b96-e9a729d7f80d","parent":"5e77df4f-4d09-45df-a9a6-35f13e6f4e28","children":[],"position":[88.70285358242472,57.49966430663426,153.45042634149286],"rotation":[0,0,0],"scale":[1,1,1],"components":{"render":{"enabled":true,"type":"asset","asset":152048765,"materialAssets":[152048467],"layers":[0],"batchGroupId":null,"castShadows":true,"castShadowsLightmap":true,"receiveShadows":true,"lightmapped":false,"lightmapSizeMultiplier":1,"castShadowsLightMap":true,"lightMapped":false,"lightMapSizeMultiplier":1,"isStatic":false,"rootBone":null}}},"1b5a3b78-f2c5-4a75-8839-a0a94411e2de":{"name":"BL_Wheel","tags":[],"enabled":true,"resource_id":"1b5a3b78-f2c5-4a75-8839-a0a94411e2de","parent":"5e77df4f-4d09-45df-a9a6-35f13e6f4e28","children":[],"position":[93.47929819403362,57.49966430663426,-159.16497069167235],"rotation":[0,0,0],"scale":[1,1,1],"components":{"render":{"enabled":true,"type":"asset","asset":152048765,"materialAssets":[152048467],"layers":[0],"batchGroupId":null,"castShadows":true,"castShadowsLightmap":true,"receiveShadows":true,"lightmapped":false,"lightmapSizeMultiplier":1,"castShadowsLightMap":true,"lightMapped":false,"lightMapSizeMultiplier":1,"isStatic":false,"rootBone":null}}},"93abe788-8004-4b59-b6f6-d6cf8719b94e":{"name":"nitro","tags":[],"enabled":true,"resource_id":"93abe788-8004-4b59-b6f6-d6cf8719b94e","parent":"29d23efa-e972-4d92-95c0-34413858a1fa","children":[],"position":[-0.6308255126423035,0.734802246093679,-3.032141568800114],"rotation":[179.9999999999999,0.6199993536903956,-180],"scale":[1,1,1],"components":{"particlesystem":{"enabled":true,"autoPlay":false,"numParticles":20,"lifetime":0.5,"rate":0,"rate2":0.1,"startAngle":0,"startAngle2":360,"loop":true,"preWarm":false,"lighting":false,"halfLambert":false,"intensity":1,"depthWrite":false,"depthSoftening":0,"sort":0,"blendType":2,"stretch":0,"alignToMotion":false,"emitterShape":0,"emitterExtents":[0.48,0,1],"emitterExtentsInner":[0,0,0],"orientation":2,"particleNormal":[0,1,0],"emitterRadius":25.96,"emitterRadiusInner":0,"initialVelocity":0,"animTilesX":1,"animTilesY":1,"animStartFrame":0,"animNumFrames":1,"animNumAnimations":1,"animIndex":0,"randomizeAnimIndex":false,"animSpeed":1,"animLoop":false,"wrap":false,"wrapBounds":[0,0,0],"colorMapAsset":152048817,"normalMapAsset":152048817,"mesh":null,"renderAsset":152048952,"localSpace":false,"screenSpace":false,"localVelocityGraph":{"type":1,"keys":[[0,0],[0,0],[0,0]],"betweenCurves":false},"localVelocityGraph2":{"type":1,"keys":[[0,0],[0,0],[0,0]]},"velocityGraph":{"type":1,"keys":[[0,-0.25],[0,0],[0,-0.1875]],"betweenCurves":true},"velocityGraph2":{"type":1,"keys":[[0,0.25],[0,0],[0,0]]},"rotationSpeedGraph":{"type":1,"keys":[0,0],"betweenCurves":false},"rotationSpeedGraph2":{"type":1,"keys":[0,0]},"radialSpeedGraph":{"type":1,"keys":[0,0],"betweenCurves":false},"radialSpeedGraph2":{"type":1,"keys":[0,0]},"scaleGraph":{"type":1,"keys":[0,0,0.3,0.003,1,0],"betweenCurves":false},"scaleGraph2":{"type":1,"keys":[0,0,0.3,0.003,1,0]},"colorGraph":{"type":4,"keys":[[0,0],[0,0.36470588235294116],[0,1]],"betweenCurves":false},"alphaGraph":{"type":2,"keys":[0,1],"betweenCurves":false},"alphaGraph2":{"type":1,"keys":[0,1]},"layers":[0]}}},"63b1d88f-d05b-4f0e-a815-0052bc1edf2b":{"name":"Smoke","tags":[],"enabled":true,"resource_id":"63b1d88f-d05b-4f0e-a815-0052bc1edf2b","parent":"29d23efa-e972-4d92-95c0-34413858a1fa","children":[],"position":[-0.9084577454302689,0.2675743103027344,-1.7116117175248178],"rotation":[179.9999999999999,0.6199993536903956,-180],"scale":[1,1,1],"components":{"particlesystem":{"enabled":true,"autoPlay":false,"numParticles":20,"lifetime":0.5,"rate":0,"rate2":0.1,"startAngle":0,"startAngle2":360,"loop":true,"preWarm":false,"lighting":false,"halfLambert":false,"intensity":1,"depthWrite":false,"depthSoftening":0,"sort":0,"blendType":2,"stretch":0,"alignToMotion":false,"emitterShape":0,"emitterExtents":[0.48,0,1],"emitterExtentsInner":[0,0,0],"orientation":2,"particleNormal":[0,1,0],"emitterRadius":25.96,"emitterRadiusInner":0,"initialVelocity":0,"animTilesX":1,"animTilesY":1,"animStartFrame":0,"animNumFrames":1,"animNumAnimations":1,"animIndex":0,"randomizeAnimIndex":false,"animSpeed":1,"animLoop":false,"wrap":false,"wrapBounds":[0,0,0],"colorMapAsset":152048817,"normalMapAsset":152048817,"mesh":null,"renderAsset":152048952,"localSpace":false,"screenSpace":false,"localVelocityGraph":{"type":1,"keys":[[0,0],[0,0],[0,0]],"betweenCurves":false},"localVelocityGraph2":{"type":1,"keys":[[0,0],[0,0],[0,0]]},"velocityGraph":{"type":1,"keys":[[0,-0.25],[0,0],[0,-0.1875]],"betweenCurves":true},"velocityGraph2":{"type":1,"keys":[[0,0.25],[0,0],[0,0]]},"rotationSpeedGraph":{"type":1,"keys":[0,0],"betweenCurves":false},"rotationSpeedGraph2":{"type":1,"keys":[0,0]},"radialSpeedGraph":{"type":1,"keys":[0,0],"betweenCurves":false},"radialSpeedGraph2":{"type":1,"keys":[0,0]},"scaleGraph":{"type":1,"keys":[0,0,0.3,0.003,1,0],"betweenCurves":false},"scaleGraph2":{"type":1,"keys":[0,0,0.3,0.003,1,0]},"colorGraph":{"type":4,"keys":[[0,1],[0,1],[0,1]],"betweenCurves":false},"alphaGraph":{"type":2,"keys":[0,1],"betweenCurves":false},"alphaGraph2":{"type":1,"keys":[0,1]},"layers":[0]},"script":{"enabled":true,"order":["coExhaust"],"scripts":{"coExhaust":{"enabled":true,"attributes":{}}}}},"template_ent_ids":{"63b1d88f-d05b-4f0e-a815-0052bc1edf2b":"2c6a063a-6a90-4134-8894-1247003690d4"},"template_id":152048947},"f94b5413-01a6-4946-9e62-ae80f911e488":{"name":"Smoke","tags":[],"enabled":true,"resource_id":"f94b5413-01a6-4946-9e62-ae80f911e488","parent":"29d23efa-e972-4d92-95c0-34413858a1fa","children":[],"position":[0.9259045269367334,0.2675743103027344,-1.8520835234083677],"rotation":[179.9999999999999,0.6199993536903956,-180],"scale":[1,1,1],"components":{"particlesystem":{"enabled":true,"autoPlay":false,"numParticles":20,"lifetime":0.5,"rate":0,"rate2":0.1,"startAngle":0,"startAngle2":360,"loop":true,"preWarm":false,"lighting":false,"halfLambert":false,"intensity":1,"depthWrite":false,"depthSoftening":0,"sort":0,"blendType":2,"stretch":0,"alignToMotion":false,"emitterShape":0,"emitterExtents":[0.48,0,1],"emitterExtentsInner":[0,0,0],"orientation":2,"particleNormal":[0,1,0],"emitterRadius":25.96,"emitterRadiusInner":0,"initialVelocity":0,"animTilesX":1,"animTilesY":1,"animStartFrame":0,"animNumFrames":1,"animNumAnimations":1,"animIndex":0,"randomizeAnimIndex":false,"animSpeed":1,"animLoop":false,"wrap":false,"wrapBounds":[0,0,0],"colorMapAsset":152048817,"normalMapAsset":152048817,"mesh":null,"renderAsset":152048952,"localSpace":false,"screenSpace":false,"localVelocityGraph":{"type":1,"keys":[[0,0],[0,0],[0,0]],"betweenCurves":false},"localVelocityGraph2":{"type":1,"keys":[[0,0],[0,0],[0,0]]},"velocityGraph":{"type":1,"keys":[[0,-0.25],[0,0],[0,-0.1875]],"betweenCurves":true},"velocityGraph2":{"type":1,"keys":[[0,0.25],[0,0],[0,0]]},"rotationSpeedGraph":{"type":1,"keys":[0,0],"betweenCurves":false},"rotationSpeedGraph2":{"type":1,"keys":[0,0]},"radialSpeedGraph":{"type":1,"keys":[0,0],"betweenCurves":false},"radialSpeedGraph2":{"type":1,"keys":[0,0]},"scaleGraph":{"type":1,"keys":[0,0,0.3,0.003,1,0],"betweenCurves":false},"scaleGraph2":{"type":1,"keys":[0,0,0.3,0.003,1,0]},"colorGraph":{"type":4,"keys":[[0,1],[0,1],[0,1]],"betweenCurves":false},"alphaGraph":{"type":2,"keys":[0,1],"betweenCurves":false},"alphaGraph2":{"type":1,"keys":[0,1]},"layers":[0]},"script":{"enabled":true,"order":["coExhaust"],"scripts":{"coExhaust":{"enabled":true,"attributes":{}}}}},"template_id":152048947,"template_ent_ids":{"f94b5413-01a6-4946-9e62-ae80f911e488":"2c6a063a-6a90-4134-8894-1247003690d4"}},"1284d79e-6c01-47da-b13e-1cdd01b45322":{"name":"sound","tags":[],"enabled":true,"resource_id":"1284d79e-6c01-47da-b13e-1cdd01b45322","parent":"29d23efa-e972-4d92-95c0-34413858a1fa","children":[],"position":[0.000006770054369553691,0,0.00000768553275065642],"rotation":[0,0,0],"scale":[1,1,1],"components":{"script":{"enabled":true,"order":[],"scripts":{}}}},"ac1d96f3-f453-4361-b30f-bb28e21e4755":{"name":"Sphere","tags":[],"enabled":true,"resource_id":"ac1d96f3-f453-4361-b30f-bb28e21e4755","parent":"5e77df4f-4d09-45df-a9a6-35f13e6f4e28","children":[],"position":[0,100,0.00008249581151176244],"rotation":[6.094595317290546e-23,0,-3.6796921531601645e-23],"scale":[750,750,750],"components":{"render":{"enabled":true,"type":"sphere","asset":null,"materialAssets":[153822333],"layers":[0],"batchGroupId":null,"castShadows":true,"castShadowsLightmap":true,"receiveShadows":true,"lightmapped":false,"lightmapSizeMultiplier":1,"castShadowsLightMap":true,"lightMapped":false,"lightMapSizeMultiplier":1,"isStatic":false,"rootBone":null},"script":{"enabled":true,"order":["coRotator"],"scripts":{"coRotator":{"enabled":true,"attributes":{"speed":[30,30,30],"rotateGlobally":false}}}}}}}}